eva-0.1.1-py3.5-nspkg.pth
eva/__init__.py
eva/cli.py
eva-0.1.1.dist-info/DESCRIPTION.rst
eva-0.1.1.dist-info/METADATA
eva-0.1.1.dist-info/RECORD
eva-0.1.1.dist-info/WHEEL
eva-0.1.1.dist-info/entry_points.txt
eva-0.1.1.dist-info/metadata.json
eva-0.1.1.dist-info/namespace_packages.txt
eva-0.1.1.dist-info/top_level.txt
virtualenvwrapper/configvars.py
